apollo_toolbox_py/__init__.py
apollo_toolbox_py/apollo_py/__init__.py
apollo_toolbox_py/apollo_py/apollo_py_array.py
apollo_toolbox_py/apollo_py/apollo_py_derivatives/__init__.py
apollo_toolbox_py/apollo_py/apollo_py_derivatives/derivative_engine.py
apollo_toolbox_py/apollo_py/apollo_py_derivatives/derivative_engine_evaluator.py
apollo_toolbox_py/apollo_py/apollo_py_derivatives/fd_derivatives.py
apollo_toolbox_py/apollo_py/apollo_py_derivatives/jax_derivatives.py
apollo_toolbox_py/apollo_py/apollo_py_derivatives/test_functions.py
apollo_toolbox_py/apollo_py/apollo_py_derivatives/wasp_derivatives.py
apollo_toolbox_py/apollo_py/apollo_py_differentiation/__init__.py
apollo_toolbox_py/apollo_py/apollo_py_differentiation/apollo_py_differentiation_tensorly/__init__.py
apollo_toolbox_py/apollo_py/apollo_py_differentiation/apollo_py_differentiation_tensorly/derivative_method_tensorly.py
apollo_toolbox_py/apollo_py/apollo_py_differentiation/apollo_py_differentiation_tensorly/function_engine_tensorly.py
apollo_toolbox_py/apollo_py/apollo_py_differentiation/apollo_py_differentiation_tensorly/function_tensorly.py
apollo_toolbox_py/apollo_py/apollo_py_differentiation/apollo_py_differentiation_tensorly/hessian_method_tensorly.py
apollo_toolbox_py/apollo_py/apollo_py_robotics/__init__.py
apollo_toolbox_py/apollo_py/apollo_py_robotics/chain.py
apollo_toolbox_py/apollo_py/apollo_py_robotics/resources_directories.py
apollo_toolbox_py/apollo_py/apollo_py_robotics/robot_functions/__init__.py
apollo_toolbox_py/apollo_py/apollo_py_robotics/robot_functions/robot_kinematics_functions.py
apollo_toolbox_py/apollo_py/apollo_py_robotics/robot_preprocessed_modules/__init__.py
apollo_toolbox_py/apollo_py/apollo_py_robotics/robot_preprocessed_modules/chain_module.py
apollo_toolbox_py/apollo_py/apollo_py_robotics/robot_preprocessed_modules/connections_module.py
apollo_toolbox_py/apollo_py/apollo_py_robotics/robot_preprocessed_modules/dof_module.py
apollo_toolbox_py-0.0.13.dist-info/LICENSE
apollo_toolbox_py-0.0.13.dist-info/METADATA
apollo_toolbox_py-0.0.13.dist-info/WHEEL
apollo_toolbox_py-0.0.13.dist-info/RECORD
