Metadata-Version: 2.1
Name: apollo-toolbox-py
Version: 0.0.13
Summary: 
License: MIT
Author: Danny Rakita
Author-email: daniel.rakita@yale.edu
Requires-Python: >=3.8,<4.0
Classifier: License :: OSI Approved :: MIT License
Classifier: Programming Language :: Python :: 3
Classifier: Programming Language :: Python :: 3.8
Classifier: Programming Language :: Python :: 3.9
Classifier: Programming Language :: Python :: 3.10
Classifier: Programming Language :: Python :: 3.11
Classifier: Programming Language :: Python :: 3.12
Classifier: Programming Language :: Python :: 3.13
Provides-Extra: all
Provides-Extra: bpy
Provides-Extra: jax
Provides-Extra: torch
Requires-Dist: bpy (>=4.3.0,<5.0.0) ; (python_version >= "3.11" and python_version < "3.12") and (extra == "all" or extra == "bpy")
Requires-Dist: easybpy (==0.0.1) ; (python_version >= "3.11" and python_version < "3.12") and (extra == "all" or extra == "bpy")
Requires-Dist: jax (>=0.4.30,<0.5.0) ; (python_version >= "3.11") and (extra == "all" or extra == "jax")
Requires-Dist: jax ; (python_version < "3.11") and (extra == "all" or extra == "jax")
Requires-Dist: mathutils ; extra == "all"
Requires-Dist: numba (>=0.60.0,<0.61.0) ; python_version >= "3.11"
Requires-Dist: numba ; python_version < "3.11"
Requires-Dist: numpy (>=2.0.1,<3.0.0) ; python_version >= "3.11"
Requires-Dist: numpy ; python_version < "3.11"
Requires-Dist: packaging (>=24.2,<25.0) ; (python_version >= "3.11") and (extra == "all")
Requires-Dist: packaging ; (python_version < "3.11") and (extra == "all")
Requires-Dist: scipy (>=1.14.0,<2.0.0) ; python_version >= "3.11"
Requires-Dist: scipy ; python_version < "3.11"
Requires-Dist: tensorly (>=0.9.0,<0.10.0) ; python_version >= "3.11"
Requires-Dist: tensorly ; python_version < "3.11"
Requires-Dist: torch (>=2.3.1,<3.0.0) ; (python_version >= "3.11") and (extra == "all" or extra == "torch")
Requires-Dist: torch ; (python_version < "3.11") and (extra == "all" or extra == "torch")
